positional_lsb/__init__.py
positional_lsb/ciphers.py
positional_lsb/exceptions.py
positional_lsb/pattern.py
positional_lsb/stego.py
positional_lsb/legacy/lsb_video.py
positional_lsb/sockets/__init__.py
positional_lsb/sockets/client.py
positional_lsb/sockets/server.py
positional_lsb/sockets/sock.py
positional_lsb-1.0.1.dist-info/METADATA
positional_lsb-1.0.1.dist-info/WHEEL
positional_lsb-1.0.1.dist-info/licenses/LICENSE
positional_lsb-1.0.1.dist-info/RECORD
