Metadata-Version: 2.1
Name: positional-lsb
Version: 1.0.1
Summary: A package for hiding data in an image using the Positional LSB algorithm
Project-URL: Homepage, https://github.com/neamaddin/positional-lsb
Project-URL: Bug Tracker, https://github.com/neamaddin/positional-lsb/issues
Author-email: Neamaddin Akhmedov <neamaddin.a@mail.ru>
License-Expression: MIT
License-File: LICENSE
Classifier: License :: OSI Approved :: MIT License
Classifier: Operating System :: OS Independent
Classifier: Programming Language :: Python :: 3
Requires-Python: >=3.10
Requires-Dist: opencv-python>=4.6.0.66
Requires-Dist: pycryptodome>=3.15.0
Provides-Extra: flake8
Requires-Dist: flake8>=6.0.0; extra == 'flake8'
Provides-Extra: mypy
Requires-Dist: mypy>=1.1.1; extra == 'mypy'
Provides-Extra: pytest
Requires-Dist: pytest-cov>=4.0.0; extra == 'pytest'
Requires-Dist: pytest-mock>=3.10.0; extra == 'pytest'
Requires-Dist: pytest>=7.2.2; extra == 'pytest'
